CHANGES.txt
MANIFEST.in
README.txt
contributors.txt
development.ini
production.ini
setup.py
travelcrm_turbosms/__init__.py
travelcrm_turbosms.egg-info/PKG-INFO
travelcrm_turbosms.egg-info/SOURCES.txt
travelcrm_turbosms.egg-info/SOURCES.txt.orig
travelcrm_turbosms.egg-info/dependency_links.txt
travelcrm_turbosms.egg-info/entry_points.txt
travelcrm_turbosms.egg-info/not-zip-safe
travelcrm_turbosms.egg-info/requires.txt
travelcrm_turbosms.egg-info/top_level.txt
travelcrm_turbosms/forms/__init__.py
travelcrm_turbosms/forms/turbosms.py
travelcrm_turbosms/lib/__init__.py
travelcrm_turbosms/lib/bl/__init__.py
travelcrm_turbosms/lib/bl/turbosms.py
travelcrm_turbosms/lib/factories/__init__.py
travelcrm_turbosms/lib/factories/turbosms.py
travelcrm_turbosms/lib/scheduler/__init__.py
travelcrm_turbosms/lib/scheduler/turbosms.py
travelcrm_turbosms/lib/subscribers/__init__.py
travelcrm_turbosms/lib/subscribers/turbosms.py
travelcrm_turbosms/locale/ru/LC_MESSAGES/travelcrm.mo
travelcrm_turbosms/locale/ru/LC_MESSAGES/travelcrm.po
travelcrm_turbosms/resources/__init__.py
travelcrm_turbosms/resources/turbosms.py
travelcrm_turbosms/templates/settings.mako
travelcrm_turbosms/views/__init__.py
travelcrm_turbosms/views/turbosms.py