Metadata-Version: 1.1
Name: travelcrm-turbosms
Version: 0.2
Summary: travelcrm_turbosms
Home-page: UNKNOWN
Author: Vitalii Mazur
Author-email: vitalii.mazur@gmail.com
License: UNKNOWN
Keywords: web pyramid pylons travelcrm sms
Platform: UNKNOWN
Classifier: Programming Language :: Python
Classifier: Framework :: Pyramid
Classifier: Topic :: Internet :: WWW/HTTP
Classifier: Topic :: Internet :: WWW/HTTP :: WSGI :: Application
